{
  "NTProvider": {
    "types": {
      "/FMSInfo": "FMSInfo"
    }
  },
  "NetworkTables": {
    "Persistent Values": {
      "open": false
    },
    "Retained Values": {
      "open": false
    },
    "transitory": {
      "Shuffleboard": {
        ".metadata": {
          "open": true
        },
        ".recording": {
          "open": true
        }
      },
      "telemetry": {
        "Arm": {
          "open": true,
          "stage1": {
            "open": true
          }
        },
        "Telescope": {
          "open": true
        },
        "open": true,
        "telescope": {
          "open": true,
          "stage1": {
            "open": true
          }
        }
      }
    }
  }
}
